TOPSIS.py
src/TOPSIS.py
src/__init__.py
TOPSIS_Shivam_101803158-0.0.3.dist-info/LICENSE.txt
TOPSIS_Shivam_101803158-0.0.3.dist-info/METADATA
TOPSIS_Shivam_101803158-0.0.3.dist-info/WHEEL
TOPSIS_Shivam_101803158-0.0.3.dist-info/entry_points.txt
TOPSIS_Shivam_101803158-0.0.3.dist-info/top_level.txt
TOPSIS_Shivam_101803158-0.0.3.dist-info/RECORD
